senso_developers/__init__.py
senso_developers/_base_client.py
senso_developers/_client.py
senso_developers/_compat.py
senso_developers/_constants.py
senso_developers/_exceptions.py
senso_developers/_files.py
senso_developers/_models.py
senso_developers/_qs.py
senso_developers/_resource.py
senso_developers/_response.py
senso_developers/_streaming.py
senso_developers/_types.py
senso_developers/_version.py
senso_developers/py.typed
senso_developers/_utils/__init__.py
senso_developers/_utils/_logs.py
senso_developers/_utils/_proxy.py
senso_developers/_utils/_reflection.py
senso_developers/_utils/_streams.py
senso_developers/_utils/_sync.py
senso_developers/_utils/_transform.py
senso_developers/_utils/_typing.py
senso_developers/_utils/_utils.py
senso_developers/lib/.keep
senso_developers/resources/__init__.py
senso_developers/resources/utils.py
senso_developers/resources/orgs/__init__.py
senso_developers/resources/orgs/documents.py
senso_developers/resources/orgs/orgs.py
senso_developers/resources/orgs/search.py
senso_developers/resources/orgs/categories/__init__.py
senso_developers/resources/orgs/categories/categories.py
senso_developers/resources/orgs/categories/tags.py
senso_developers/resources/orgs/collections/__init__.py
senso_developers/resources/orgs/collections/collections.py
senso_developers/resources/orgs/collections/documents.py
senso_developers/types/__init__.py
senso_developers/types/org.py
senso_developers/types/org_create_params.py
senso_developers/types/org_list.py
senso_developers/types/org_update_params.py
senso_developers/types/orgs/__init__.py
senso_developers/types/orgs/category.py
senso_developers/types/orgs/category_create_params.py
senso_developers/types/orgs/category_list_response.py
senso_developers/types/orgs/category_update_params.py
senso_developers/types/orgs/chunk_pages.py
senso_developers/types/orgs/collection.py
senso_developers/types/orgs/collection_create_params.py
senso_developers/types/orgs/collection_list.py
senso_developers-0.0.1a2.dist-info/METADATA
senso_developers-0.0.1a2.dist-info/WHEEL
senso_developers-0.0.1a2.dist-info/licenses/LICENSE
senso_developers-0.0.1a2.dist-info/RECORD
